nile_api/__init__.py
nile_api/client.py
nile_api/events.py
nile_api/py.typed
nile_api/types.py
nile_api/api/__init__.py
nile_api/api/access/__init__.py
nile_api/api/access/create_policy.py
nile_api/api/access/delete_policy.py
nile_api/api/access/get_policy.py
nile_api/api/access/list_policies.py
nile_api/api/access/update_policy.py
nile_api/api/developers/__init__.py
nile_api/api/developers/create_developer.py
nile_api/api/developers/developer_google_o_auth_callback.py
nile_api/api/developers/login_developer.py
nile_api/api/developers/start_developer_google_o_auth.py
nile_api/api/developers/validate_developer.py
nile_api/api/entities/__init__.py
nile_api/api/entities/create_entity.py
nile_api/api/entities/create_instance.py
nile_api/api/entities/delete_instance.py
nile_api/api/entities/get_entity.py
nile_api/api/entities/get_instance.py
nile_api/api/entities/get_open_api.py
nile_api/api/entities/instance_events.py
nile_api/api/entities/list_entities.py
nile_api/api/entities/list_instances.py
nile_api/api/entities/list_instances_in_workspace.py
nile_api/api/entities/update_entity.py
nile_api/api/entities/update_instance.py
nile_api/api/metrics/__init__.py
nile_api/api/metrics/aggregate_metrics.py
nile_api/api/metrics/filter_metrics.py
nile_api/api/metrics/filter_metrics_for_entity_type.py
nile_api/api/metrics/list_metric_definitions.py
nile_api/api/metrics/list_metric_definitions_for_entity_type.py
nile_api/api/metrics/produce_batch_of_metrics.py
nile_api/api/organizations/__init__.py
nile_api/api/organizations/accept_invite.py
nile_api/api/organizations/add_user_to_org.py
nile_api/api/organizations/create_organization.py
nile_api/api/organizations/delete_organization.py
nile_api/api/organizations/get_organization.py
nile_api/api/organizations/list_invites.py
nile_api/api/organizations/list_organizations.py
nile_api/api/organizations/list_users_in_org.py
nile_api/api/organizations/remove_user_from_org.py
nile_api/api/organizations/update_organization.py
nile_api-0.2.8.dist-info/METADATA
nile_api-0.2.8.dist-info/WHEEL
nile_api-0.2.8.dist-info/licenses/LICENSE
nile_api-0.2.8.dist-info/RECORD
