Metadata-Version: 2.1
Name: nile-api
Version: 0.2.8
Summary: A client library for accessing the Nile API
Project-URL: Homepage, https://www.thenile.dev/
Project-URL: Issues, https://github.com/TheNileDev/nile-py/issues/
Project-URL: Source, https://github.com/TheNileDev/nile-py
Author: The Nile
Author-email: support@thenile.dev
License: MIT
License-File: LICENSE
Keywords: client,control plane,infrastructure,openapi,saas
Classifier: Development Status :: 4 - Beta
Classifier: License :: OSI Approved :: MIT License
Classifier: Operating System :: OS Independent
Classifier: Programming Language :: Python
Classifier: Programming Language :: Python :: 3
Classifier: Programming Language :: Python :: 3.7
Classifier: Programming Language :: Python :: 3.8
Classifier: Programming Language :: Python :: 3.9
Classifier: Programming Language :: Python :: 3.10
Classifier: Programming Language :: Python :: 3.11
Classifier: Programming Language :: Python :: Implementation :: CPython
Classifier: Programming Language :: Python :: Implementation :: PyPy
Requires-Python: >=3.7
Requires-Dist: attrs
Requires-Dist: httpx
Requires-Dist: python-dateutil
